MANIFEST.in
documentation.html
license.txt
setup.py
CompoundPye/__init__.py
CompoundPye/system.py
CompoundPye.egg-info/PKG-INFO
CompoundPye.egg-info/SOURCES.txt
CompoundPye.egg-info/dependency_links.txt
CompoundPye.egg-info/not-zip-safe
CompoundPye.egg-info/requires.txt
CompoundPye.egg-info/top_level.txt
CompoundPye/Analyzer/__init__.py
CompoundPye/Analyzer/analyze_compare.py
CompoundPye/Analyzer/analyzer.py
CompoundPye/Circuits/__init__.py
CompoundPye/Circuits/circuit.py
CompoundPye/Components/__init__.py
CompoundPye/Components/array_transfer_functions.py
CompoundPye/Components/component.py
CompoundPye/Components/highpass_filter.py
CompoundPye/Components/linear_input_filter.py
CompoundPye/Components/lowpass_filter.py
CompoundPye/Components/transfer_functions.py
CompoundPye/Components/Connections/__init__.py
CompoundPye/Components/Connections/connection.py
CompoundPye/GUI/__init__.py
CompoundPye/GUI/circuit_editor.py
CompoundPye/GUI/default_values.pkl
CompoundPye/GUI/help_widget.py
CompoundPye/GUI/main_gui.py
CompoundPye/GUI/sensor_editor.py
CompoundPye/GUI/stimuli_editor.py
CompoundPye/GUI/styles.py
CompoundPye/GUI/ui_tabs.py
CompoundPye/Graph/__init__.py
CompoundPye/Graph/sensors.py
CompoundPye/Graph/sensors_old.py
CompoundPye/OmmatidialMap/SphereCoord.mat
CompoundPye/OmmatidialMap/SphereCoordB.mat
CompoundPye/OmmatidialMap/SphereCoordCalli.mat
CompoundPye/OmmatidialMap/__init__.py
CompoundPye/OmmatidialMap/accpAngle.mat
CompoundPye/OmmatidialMap/accpAngleGaussFit.mat
CompoundPye/OmmatidialMap/bee_gauss_coeffs.npy
CompoundPye/OmmatidialMap/bee_sphere_coords_spheric.npy
CompoundPye/OmmatidialMap/droso_gauss_coeffs.npy
CompoundPye/OmmatidialMap/droso_sphere_coords_spheric.npy
CompoundPye/OmmatidialMap/old_droso_gauss_coeffs.npy
CompoundPye/OmmatidialMap/read_bee_mat.py
CompoundPye/OmmatidialMap/read_droso.py
CompoundPye/OmmatidialMap/read_droso_mat.py
CompoundPye/OmmatidialMap/read_ommatidia.py
CompoundPye/Parser/__init__.py
CompoundPye/Parser/circuit_parser.py
CompoundPye/Parser/creator.py
CompoundPye/Parser/paths_to.py
CompoundPye/Parser/sensor_parser.py
CompoundPye/Parser/stimuli_creator.py
CompoundPye/Sensors/__init__.py
CompoundPye/Sensors/create_array.py
